nornir_maze/__init__.py
nornir_maze/git.py
nornir_maze/utils.py
nornir_maze/cisco_support/__init__.py
nornir_maze/cisco_support/api_calls.py
nornir_maze/cisco_support/reports.py
nornir_maze/cisco_support/utils.py
nornir_maze/configuration_management/__init__.py
nornir_maze/configuration_management/pyats.py
nornir_maze/configuration_management/utils.py
nornir_maze/configuration_management/cli/__init__.py
nornir_maze/configuration_management/cli/config_tasks.py
nornir_maze/configuration_management/cli/config_workflow.py
nornir_maze/configuration_management/cli/show_tasks.py
nornir_maze/configuration_management/netconf/__init__.py
nornir_maze/configuration_management/netconf/config_tasks.py
nornir_maze/configuration_management/netconf/config_workflow.py
nornir_maze/configuration_management/netconf/ops_tasks.py
nornir_maze/configuration_management/restconf/__init__.py
nornir_maze/configuration_management/restconf/cisco_rpc.py
nornir_maze/configuration_management/restconf/config_workflow.py
nornir_maze/configuration_management/restconf/tasks.py
nornir_maze/software_upgrade/__init__.py
nornir_maze/software_upgrade/nr_software_upgrade.py
nornir_maze/software_upgrade/utils.py
nornir_maze-0.0.115.dist-info/LICENSE
nornir_maze-0.0.115.dist-info/METADATA
nornir_maze-0.0.115.dist-info/WHEEL
nornir_maze-0.0.115.dist-info/top_level.txt
nornir_maze-0.0.115.dist-info/RECORD
