Metadata-Version: 2.1
Name: nornir-maze
Version: 0.0.115
Summary: Nornir_maze is a collection of Nornir tasks and general functions in Nornir stdout style.
Home-page: https://github.com/willikubny/nornir-maze
Author: Willi Kubny
Author-email: willi.kubny@gmail.com
Project-URL: Repository, https://github.com/willikubny/nornir-maze
Project-URL: Bug Tracker, https://github.com/willikubny/nornir-maze/issues
Classifier: Programming Language :: Python :: 3
Classifier: License :: OSI Approved :: MIT License
Classifier: Operating System :: OS Independent
Requires-Python: >=3.6
License-File: LICENSE
Requires-Dist: pre-commit (==2.20.0)
Requires-Dist: pyfiglet (==0.8.post1)
Requires-Dist: PyYAML (==6.0)
Requires-Dist: GitPython (==3.1.18)
Requires-Dist: cisco-support (==0.3.1)
Requires-Dist: nornir (==3.3.0)
Requires-Dist: nornir-jinja2 (==0.2.0)
Requires-Dist: nornir-netmiko (==0.2.0)
Requires-Dist: nornir-salt (==0.16.1)
Requires-Dist: nornir-scrapli (==2022.7.30)
Requires-Dist: nornir-utils (==0.2.0)
Requires-Dist: scrapli-ssh2 (==2020.10.24)
Requires-Dist: scrapli-netconf (==2022.7.30)
Requires-Dist: pyats (==22.10)
Requires-Dist: genie (==22.10)
Requires-Dist: openpyxl (==3.0.10)
Requires-Dist: XlsxWriter (==3.0.3)
Requires-Dist: yaspin (==2.2.0)
Requires-Dist: requests (==2.28.1)
Requires-Dist: pandas (==1.5.1)
Requires-Dist: tabulate (==0.9.0)
Requires-Dist: black (==22.10.0)
Requires-Dist: yamllint (==1.28.0)
Requires-Dist: pylint (==2.15.5)
Requires-Dist: prospector (==1.7.7)
Requires-Dist: bandit (==1.7.4)
Requires-Dist: vulture (==2.6)
